chiral_transfermatrix/__init__.py
chiral_transfermatrix-0.1.2.dist-info/LICENSE
chiral_transfermatrix-0.1.2.dist-info/WHEEL
chiral_transfermatrix-0.1.2.dist-info/METADATA
chiral_transfermatrix-0.1.2.dist-info/RECORD
