Metadata-Version: 2.1
Name: chiral-transfermatrix
Version: 0.1.2
Summary: chiral-transfermatrix is a transfer/scattering matrix package for calculating the optical response of achiral and chiral multilayer structures.
Author: Lorenzo Mauro, Jacopo Fregoni, Remi Avriller
Author-email: Johannes Feist <johannes.feist@gmail.com>
Requires-Python: >=3.8
Classifier: License :: OSI Approved :: MIT License
Requires-Dist: numpy >=1.15
Project-URL: Home, https://github.com/jfeist/chiral-transfermatrix
